rocketry_py/__init__.py
rocketry_py/simple.py
rocketry_py/universal/__init__.py
rocketry_py/universal/constants.py
rocketry_py/universal/functions.py
rocketry_py-0.1.0.dist-info/METADATA
rocketry_py-0.1.0.dist-info/WHEEL
rocketry_py-0.1.0.dist-info/RECORD
