Metadata-Version: 2.3
Name: rocketry-py
Version: 0.1.0
Summary: A Python library for rocketry related calculations
Author: henceiusegentoo
Author-email: 61363222+henceiusegentoo@users.noreply.github.com
Requires-Python: >=3.13
Classifier: Programming Language :: Python :: 3
Classifier: Programming Language :: Python :: 3.13
Requires-Dist: numpy (>=2.2.3,<3.0.0)
